{"key":"Antiswarm Grenade, V","url":"https://www.aonsrd.com/WeaponDisplay.aspx?ItemName=V&Family=Antiswarm Grenade","family":"Antiswarm Grenade","name_en":"Antiswarm Grenade, V","description_en":"The sticky, caustic substance that sputters from this device burns skin and armor alike. On a failed Reflex saving throw, for 1d4 rounds, any creature with the swarm defenses universal creature rule takes half damage from single target attacks or effects that it would normally be immune to. On a failed Reflex saving throw, for 1d4 rounds, any creature with the troop defenses ability receives full damage from single target attacks, and can be targeted by effects that target a specific number of creatures.","source":"Starfinder Enhanced pg. 165","level":"13","price":"7,400","hands":"1","proficiency":"Grenade","category":"","damage":"—","damageType":[],"critical":"—","bulk":"L","special":["Explode (6d6 A","15 ft.","see text)"],"capacity":"Drawn"}