{
	"key": "Autobeam Rifle, Elite",
	"url": "https://www.aonsrd.com/WeaponDisplay.aspx?ItemName=Elite&Family=Autobeam Rifle",
	"family": "Autobeam Rifle",
	"name_en": "Autobeam Rifle, Elite",
	"description_en": "Autobeam rifles can fire in automatic mode, spraying a cone of lasers from the barrel.",
	"source": "Starfinder Core Rulebook pg. 176",
	"level": "15",
	"price": "95,500",
	"hands": "2",
	"proficiency": "Longarms",
	"category": "Laser",
	"damage": "7d4",
	"damageType": [
		"F"
	],
	"critical": "burn 3d4",
	"bulk": "2",
	"special": [
		"automatic"
	],
	"capacity": "100 charges"
}