{
	"key": "Tomb Claw, Ghoulish",
	"url": "https://www.aonsrd.com/WeaponDisplay.aspx?ItemName=Ghoulish&Family=Tomb Claw",
	"family": "Tomb Claw",
	"name_en": "Tomb Claw, Ghoulish",
	"description_en": "Corpse Fleet officers directing hordes of converted covet these wicked talons. Powered by a built-in energy pack, these melee weapons resemble skeletal claws made of bone and steel. The claw weeps frost in areas with an atmosphere, and its touch freezes the skin of any living creature it strikes.",
	"source": "Starfinder Dead Suns Adventure Path pg. 247, Starfinder #3: Splintered Worlds pg. 49",
	"level": "16",
	"price": "170,100",
	"hands": "1",
	"proficiency": "Advanced Melee",
	"category": "Cryo",
	"damage": "12d4",
	"damageType": [
		"P",
		"C"
	],
	"critical": "—",
	"bulk": "1",
	"special": [
		"necrotic",
		"powered (capacity 20 usage 1)"
	],
	"capacity": ""
}